fullAdder/fullAdder.v
`timescale 1ns / 1ps
module full_adder (
    input a,
    input b,
    input c_in,
    output wire sum,
    output wire carry_out
);

// Assign sum
assign sum = a ^ b ^ c_in;
// Assign carry_out
assign carry_out = (a & b) | (a & c_in) | (c_in & b);

endmodule

fullAdder/fullAdderTB.v
`timescale 1ns / 1ps
module tb_full_adder;

    // Declare testbench signals
    reg a, b, c_in;
    wire sum, carry_out;

    // Instantiate the full-adder module
    full_adder dut (a, b, c_in, sum, carry_out);

    // Dumpfile & dumpvars for waveform generation
    initial begin
        $dumpfile("fullAdderTB.vcd"); // Specify dump filename
        $dumpvars(0, tb_full_adder); // Dump all signals in the testbench
    end


    // Apply test stimulus
    initial begin
        $display("Testing Full Adder");
        $monitor("a = %b, b = %b, c_in = %b, sum = %b, carry_out = %b", a, b, c_in, sum, carry_out);

        // Apply all possible binary permutations for four binary inputs a, b, c_in
        a = 0; b = 0; c_in = 0; #10;
        a = 0; b = 0; c_in = 1; #10;
        a = 0; b = 1; c_in = 0; #10;
        a = 0; b = 1; c_in = 1; #10;
        a = 1; b = 0; c_in = 0; #10;
        a = 1; b = 0; c_in = 1; #10;
        a = 1; b = 1; c_in = 0; #10;
        a = 1; b = 1; c_in = 1; #10;

        $finish;
    end

endmodule

fullAdder/fullAdderTB.vcd
$date
	Thu Mar 12 19:38:50 2026
$end
$version
	Icarus Verilog
$end
$timescale
	1ps
$end
$scope module tb_full_adder $end
$var wire 1 ! sum $end
$var wire 1 " carry_out $end
$var reg 1 # a $end
$var reg 1 $ b $end
$var reg 1 % c_in $end
$scope module dut $end
$var wire 1 # a $end
$var wire 1 $ b $end
$var wire 1 % c_in $end
$var wire 1 " carry_out $end
$var wire 1 ! sum $end
$upscope $end
$upscope $end
$enddefinitions $end
$comment Show the parameter values. $end
$dumpall
$end
#0
$dumpvars
0%
0$
0#
0"
0!
$end
#10000
1!
1%
#20000
0%
1$
#30000
1"
0!
1%
#40000
0"
1!
0%
0$
1#
#50000
1"
0!
1%
#60000
0%
1$
#70000
1!
1%
